{
  "symptom": "발바닥 통증",
  "questions": [
    {
      "question": "언제부터 발바닥이 아팠나요?",
      "options": ["오늘", "며칠 전부터", "1주 이상"]
    },
    {
      "question": "통증 부위는 어디인가요?",
      "options": ["뒤꿈치", "발볼", "발가락 밑", "전체"]
    },
    {
      "question": "통증의 양상은?",
      "options": ["찌르는 느낌", "타는 듯", "둔통", "간헐적"]
    },
    {
      "question": "걸을 때와 휴식 시 통증이 다르나요?",
      "options": ["걸을 때 더 아픔", "휴식 때 더 아픔", "변화 없음"]
    },
    {
      "question": "동반 증상(붓기, 발적 등)이 있나요?",
      "options": ["부기", "발적", "감각 저하", "없음"]
    }
  ]
}