{
  "symptom": "피부 각질",
  "questions": [
    {
      "question": "언제부터 각질이 많아졌나요?",
      "options": ["오늘", "며칠 전부터", "1주 이상"]
    },
    {
      "question": "주로 각질이 많은 부위는 어디인가요?",
      "options": ["두피", "얼굴", "팔/다리", "흉부/등"]
    },
    {
      "question": "각질과 함께 가려움이나 붉어짐이 있나요?",
      "options": ["가려움", "홍반", "건조", "없음"]
    },
    {
      "question": "각질 제거를 위해 시도해 본 방법이 있나요?",
      "options": ["스크럽", "보습제", "샴푸 교체", "없음"]
    },
    {
      "question": "완화 효과를 본 방법이 있나요?",
      "options": ["예, 효과 있음", "부분적 효과", "효과 없음", "시도 안 함"]
    }
  ]
}